[
    {
        "nombre": "",
        "apellido": ""
    },
    {
        "nombre": "jose",
        "apellido": "martinez"
    },
    {
        "nombre": "jose",
        "apellido": "martinez"
    },
    {
        "nombre": "",
        "apellido": ""
    },
    {
        "nombre": "PEDRO PABLO",
        "apellido": "RODRIGUEZ GOMEZ"
    },
    {
        "nombre": "PEDRO PABLO",
        "apellido": "RODRIGUEZ GOMEZ"
    },
    {
        "nombre": "PEDRO PABLO",
        "apellido": "RODRIGUEZ GOMEZ"
    },
    {
        "nombre": "lupe",
        "apellido": "chuy"
    },
    {
        "nombre": "lupe",
        "apellido": "chuy"
    },
    {
        "nombre": "lupe",
        "apellido": "chuy"
    },
    {
        "nombre": "lupe",
        "apellido": "chuy"
    },
    {
        "nombre": "lupe",
        "apellido": "chuy"
    },
    {
        "nombre": "lupe",
        "apellido": "chuy"
    },
    {
        "nombre": "lupe",
        "apellido": "chuy"
    },
    {
        "nombre": "lupe",
        "apellido": "chuy"
    },
    {
        "nombre": "lupe",
        "apellido": "chuy"
    },
    {
        "nombre": "lupe",
        "apellido": "chuy"
    },
    {
        "nombre": "ramiro",
        "apellido": "mendoza"
    },
    {
        "nombre": "carolina",
        "apellido": "parrales"
    },
    {
        "nombre": "carolina",
        "apellido": "parrales"
    },
    {
        "nombre": "carolina",
        "apellido": "parrales"
    },
    {
        "nombre": "carlos ",
        "apellido": "suarez"
    }
]